__init__.py
__version__.py
djangoaddicts/__init__.py
djangoaddicts/pygwalker/__init__.py
djangoaddicts/pygwalker/apps.py
djangoaddicts/pygwalker/forms.py
djangoaddicts/pygwalker/urls.py
djangoaddicts/pygwalker/views.py
djangoaddicts/pygwalker/templates/pygwalker/bs5/pygwalker.html
djangoaddicts/pygwalker/templates/pygwalker/bs5/pygwalker_dynamic.html
djangoaddicts/pygwalker/templates/pygwalker/bs5/partials/file_upload.htm
djangoaddicts/pygwalker/templates/pygwalker/bs5/partials/footer.htm
djangoaddicts/pygwalker/templates/pygwalker/bs5/partials/header.htm
djangoaddicts/pygwalker/templates/pygwalker/bs5/partials/pyg.htm
djangoaddicts/pygwalker/templates/pygwalker/bs5/partials/pygwalker_nav_menu.htm
django_pygwalker-0.0.9.dist-info/LICENSE
django_pygwalker-0.0.9.dist-info/METADATA
django_pygwalker-0.0.9.dist-info/WHEEL
django_pygwalker-0.0.9.dist-info/top_level.txt
django_pygwalker-0.0.9.dist-info/RECORD
