Metadata-Version: 2.1
Name: django-pygwalker
Version: 0.0.9
Summary: PyGWalker views for Django projects
Author-email: David Slusser <dbslusser@gmail.com>
License: GNU GENERAL PUBLIC LICENSE
Project-URL: homepage, https://github.com/djangoaddicts/django-pygwalker
Project-URL: repository, https://github.com/djangoaddicts/django-pygwalker
Keywords: django,visualization,data-analysis,data-exploration,tableau,tableau-alternative
Classifier: Development Status :: 5 - Production/Stable
Classifier: Environment :: Web Environment
Classifier: Framework :: Django
Classifier: Framework :: Django :: 3.2
Classifier: Framework :: Django :: 4.0
Classifier: Framework :: Django :: 4.1
Classifier: Framework :: Django :: 4.2
Classifier: Intended Audience :: Developers
Classifier: Operating System :: OS Independent
Classifier: Programming Language :: Python
Classifier: Programming Language :: Python :: 3 :: Only
Classifier: Programming Language :: Python :: 3.8
Classifier: Programming Language :: Python :: 3.9
Classifier: Programming Language :: Python :: 3.10
Classifier: Programming Language :: Python :: 3.11
Classifier: Topic :: Software Development :: Libraries :: Python Modules
Requires-Python: >=3.8
License-File: LICENSE
Requires-Dist: django
Requires-Dist: django-handyhelpers>=0.3.10
Requires-Dist: pandas
Requires-Dist: pygwalker
Provides-Extra: dev
Requires-Dist: bandit; extra == "dev"
Requires-Dist: black; extra == "dev"
Requires-Dist: build; extra == "dev"
Requires-Dist: coveralls; extra == "dev"
Requires-Dist: django-environ; extra == "dev"
Requires-Dist: isort; extra == "dev"
Requires-Dist: model-bakery; extra == "dev"
Requires-Dist: mypy; extra == "dev"
Requires-Dist: mypy-extensions; extra == "dev"
Requires-Dist: ruff; extra == "dev"
Requires-Dist: pytest; extra == "dev"
Requires-Dist: pytest-cov; extra == "dev"
Requires-Dist: pytest-django; extra == "dev"
Requires-Dist: radon; extra == "dev"
Requires-Dist: safety; extra == "dev"
Requires-Dist: setuptools>=67.7.2; extra == "dev"
Requires-Dist: setuptools-scm>=7.1; extra == "dev"
Requires-Dist: tox; extra == "dev"
Requires-Dist: tox-gh-actions; extra == "dev"
Requires-Dist: types-python-dateutil; extra == "dev"
Requires-Dist: typing-extensions; extra == "dev"
Requires-Dist: wheel>=0.40.0; extra == "dev"
Provides-Extra: docs
Requires-Dist: sphinx; extra == "docs"
Requires-Dist: sphinx-rtd-theme; extra == "docs"
Requires-Dist: myst-parser; extra == "docs"
